kconfigstyle/__init__.py
kconfigstyle/__main__.py
kconfigstyle-0.6.2.dist-info/WHEEL
kconfigstyle-0.6.2.dist-info/entry_points.txt
kconfigstyle-0.6.2.dist-info/METADATA
kconfigstyle-0.6.2.dist-info/RECORD
