Metadata-Version: 2.4
Name: kconfigstyle
Version: 0.6.2
Summary: Simple formatter for Kconfig files
License-Expression: MIT
Requires-Python: >=3.10
Project-URL: Homepage, https://github.com/noahp/kconfigstyle
Project-URL: Issues, https://github.com/noahp/kconfigstyle/issues
Project-URL: Repository, https://github.com/noahp/kconfigstyle
